[
  {
    "id": "gid://shopify/MediaImage/1593307299863",
    "type": "MediaImage",
    "mediaContentType": "IMAGE",
    "status": "READY",
    "alt": "",
    "embeddedUrl": null,
    "host": null,
    "originUrl": null,
    "image": {
      "url": "https://cdn.shopify.com/s/files/1/0065/5484/5248/products/image_25.jpg?v=1544741922",
      "altText": "",
      "width": 1024,
      "height": 1024
    },
    "sources": [],
    "localPath": "catalog/shopify/products/cyclops/media/01-cyclops.jpg"
  },
  {
    "id": "gid://shopify/MediaImage/1593307332631",
    "type": "MediaImage",
    "mediaContentType": "IMAGE",
    "status": "READY",
    "alt": "",
    "embeddedUrl": null,
    "host": null,
    "originUrl": null,
    "image": {
      "url": "https://cdn.shopify.com/s/files/1/0065/5484/5248/products/image_36.png?v=1544741924",
      "altText": "",
      "width": 1024,
      "height": 1024
    },
    "sources": [],
    "localPath": "catalog/shopify/products/cyclops/media/02-cyclops.png"
  },
  {
    "id": "gid://shopify/MediaImage/1593307398167",
    "type": "MediaImage",
    "mediaContentType": "IMAGE",
    "status": "READY",
    "alt": "",
    "embeddedUrl": null,
    "host": null,
    "originUrl": null,
    "image": {
      "url": "https://cdn.shopify.com/s/files/1/0065/5484/5248/products/image_37.png?v=1544741926",
      "altText": "",
      "width": 1024,
      "height": 1024
    },
    "sources": [],
    "localPath": "catalog/shopify/products/cyclops/media/03-cyclops.png"
  }
]
